setup.py
flask_middleware_jwt/__init__.py
flask_middleware_jwt.egg-info/PKG-INFO
flask_middleware_jwt.egg-info/SOURCES.txt
flask_middleware_jwt.egg-info/dependency_links.txt
flask_middleware_jwt.egg-info/requires.txt
flask_middleware_jwt.egg-info/top_level.txt